[
  {
    "alpha_two_code": "RO",
    "state-province": null,
    "country": "Romania",
    "domains": [
      "aistedaab.ro"
    ],
    "web_pages": [
      "http://www.aistedaab.ro/"
    ],
    "name": "AISTEDA"
  },
  {
    "alpha_two_code": "RO",
    "state-province": null,
    "country": "Romania",
    "domains": [
      "amgd.eu"
    ],
    "web_pages": [
      "http://www.amgd.eu/"
    ],
    "name": "Academy of Music \"Georghe Dima\" Cluj-Napoca"
  },
  {
    "alpha_two_code": "RO",
    "state-province": null,
    "country": "Romania",
    "domains": [
      "anefs-edu.ro"
    ],
    "web_pages": [
      "http://www.anefs-edu.ro/"
    ],
    "name": "National Academy for Physical Education and Sports Bucharest"
  },
  {
    "alpha_two_code": "RO",
    "state-province": null,
    "country": "Romania",
    "domains": [
      "arteiasi.ro"
    ],
    "web_pages": [
      "http://www.arteiasi.ro/"
    ],
    "name": "Academy of Arts \"George Enescu\" Iasi"
  },
  {
    "alpha_two_code": "RO",
    "state-province": null,
    "country": "Romania",
    "domains": [
      "ase.ro"
    ],
    "web_pages": [
      "http://www.ase.ro/"
    ],
    "name": "Academia de Studii Economice din Bucuresti"
  },
  {
    "alpha_two_code": "RO",
    "state-province": null,
    "country": "Romania",
    "domains": [
      "central.ucv.ro"
    ],
    "web_pages": [
      "http://www.central.ucv.ro/"
    ],
    "name": "University of Craiova"
  },
  {
    "alpha_two_code": "RO",
    "state-province": null,
    "country": "Romania",
    "domains": [
      "emanuel.ro"
    ],
    "web_pages": [
      "http://www.emanuel.ro/"
    ],
    "name": "Emanuel University"
  },
  {
    "alpha_two_code": "RO",
    "state-province": null,
    "country": "Romania",
    "domains": [
      "iaim.ro"
    ],
    "web_pages": [
      "http://www.iaim.ro/"
    ],
    "name": "Institute of Architecture \"Ion Mincu\" Bucharest"
  },
  {
    "alpha_two_code": "RO",
    "state-province": null,
    "country": "Romania",
    "domains": [
      "mta.ro"
    ],
    "web_pages": [
      "http://www.mta.ro/"
    ],
    "name": "Academia Tehnica Militara"
  },
  {
    "alpha_two_code": "RO",
    "state-province": null,
    "country": "Romania",
    "domains": [
      "oradeauniversity.com"
    ],
    "web_pages": [
      "http://www.oradeauniversity.com/"
    ],
    "name": "University of Medicine and Pharmacology of Oradea"
  },
  {
    "alpha_two_code": "RO",
    "state-province": null,
    "country": "Romania",
    "domains": [
      "oradeauniversity.co"
    ],
    "web_pages": [
      "http://www.oradeauniversity.com"
    ],
    "name": "Oradea University"
  },
  {
    "alpha_two_code": "RO",
    "state-province": null,
    "country": "Romania",
    "domains": [
      "ovidunivconstanta-edu.org"
    ],
    "web_pages": [
      "http://www.ovidunivconstanta-edu.org/"
    ],
    "name": "University of Constanta Medical School"
  },
  {
    "alpha_two_code": "RO",
    "state-province": null,
    "country": "Romania",
    "domains": [
      "pub.ro"
    ],
    "web_pages": [
      "http://www.pub.ro/"
    ],
    "name": "University Politehnica of Bucharest"
  },
  {
    "alpha_two_code": "RO",
    "state-province": null,
    "country": "Romania",
    "domains": [
      "rau.ro"
    ],
    "web_pages": [
      "http://www.rau.ro/"
    ],
    "name": "Romanian-American University"
  },
  {
    "alpha_two_code": "RO",
    "state-province": null,
    "country": "Romania",
    "domains": [
      "sibiu.ro"
    ],
    "web_pages": [
      "http://www.sibiu.ro/"
    ],
    "name": "University of Sibiu"
  },
  {
    "alpha_two_code": "RO",
    "state-province": null,
    "country": "Romania",
    "domains": [
      "snspa.ro"
    ],
    "web_pages": [
      "http://www.snspa.ro/"
    ],
    "name": "National School of Political and Administrative Studies Bucharest"
  },
  {
    "alpha_two_code": "RO",
    "state-province": null,
    "country": "Romania",
    "domains": [
      "spiruharet.ro"
    ],
    "web_pages": [
      "http://www.spiruharet.ro/"
    ],
    "name": "Spiru Haret University"
  },
  {
    "alpha_two_code": "RO",
    "state-province": null,
    "country": "Romania",
    "domains": [
      "tuiasi.ro"
    ],
    "web_pages": [
      "http://www.tuiasi.ro/"
    ],
    "name": "Technical University of Iasi"
  },
  {
    "alpha_two_code": "RO",
    "state-province": null,
    "country": "Romania",
    "domains": [
      "uab.ro"
    ],
    "web_pages": [
      "http://www.uab.ro/"
    ],
    "name": "1 December University of Alba Iulia"
  },
  {
    "alpha_two_code": "RO",
    "state-province": null,
    "country": "Romania",
    "domains": [
      "uaic.ro"
    ],
    "web_pages": [
      "http://www.uaic.ro/"
    ],
    "name": "University of Iasi"
  },
  {
    "alpha_two_code": "RO",
    "state-province": null,
    "country": "Romania",
    "domains": [
      "uartdcluj.ro"
    ],
    "web_pages": [
      "http://www.uartdcluj.ro/"
    ],
    "name": "University of Art and Design Cluj-Napoca"
  },
  {
    "alpha_two_code": "RO",
    "state-province": null,
    "country": "Romania",
    "domains": [
      "uat.ro"
    ],
    "web_pages": [
      "http://www.uat.ro/"
    ],
    "name": "Targu-Mures University of Theatre"
  },
  {
    "alpha_two_code": "RO",
    "state-province": null,
    "country": "Romania",
    "domains": [
      "uav.ro"
    ],
    "web_pages": [
      "http://www.uav.ro/"
    ],
    "name": "University \"Aurel Vlaicu\" Arad"
  },
  {
    "alpha_two_code": "RO",
    "state-province": null,
    "country": "Romania",
    "domains": [
      "ubbcluj.ro"
    ],
    "web_pages": [
      "http://www.ubbcluj.ro/"
    ],
    "name": "Babes-Bolyai University of Cluj-Napoca"
  },
  {
    "alpha_two_code": "RO",
    "state-province": null,
    "country": "Romania",
    "domains": [
      "ubm.ro"
    ],
    "web_pages": [
      "http://www.ubm.ro/"
    ],
    "name": "North University of Baia Mare"
  },
  {
    "alpha_two_code": "RO",
    "state-province": null,
    "country": "Romania",
    "domains": [
      "ub.ro"
    ],
    "web_pages": [
      "http://www.ub.ro/"
    ],
    "name": "University of Bacau"
  },
  {
    "alpha_two_code": "RO",
    "state-province": null,
    "country": "Romania",
    "domains": [
      "uem.ro"
    ],
    "web_pages": [
      "http://www.uem.ro/"
    ],
    "name": "University of Resita"
  },
  {
    "alpha_two_code": "RO",
    "state-province": null,
    "country": "Romania",
    "domains": [
      "ugal.ro"
    ],
    "web_pages": [
      "http://www.ugal.ro/"
    ],
    "name": "University of Galatzi"
  },
  {
    "alpha_two_code": "RO",
    "state-province": null,
    "country": "Romania",
    "domains": [
      "ulbsibiu.ro"
    ],
    "web_pages": [
      "http://www.ulbsibiu.ro/"
    ],
    "name": "University Lucian Blaga of Sibiu"
  },
  {
    "alpha_two_code": "RO",
    "state-province": null,
    "country": "Romania",
    "domains": [
      "umfcluj.ro"
    ],
    "web_pages": [
      "http://www.umfcluj.ro/"
    ],
    "name": "University of Medicine and Pharmacy of Cluj-Napoca"
  },
  {
    "alpha_two_code": "RO",
    "state-province": null,
    "country": "Romania",
    "domains": [
      "umfiasi.ro"
    ],
    "web_pages": [
      "http://www.umfiasi.ro/"
    ],
    "name": "University of Medicine and Pharmacy of Iasi"
  },
  {
    "alpha_two_code": "RO",
    "state-province": null,
    "country": "Romania",
    "domains": [
      "umftgm.ro"
    ],
    "web_pages": [
      "http://www.umftgm.ro/"
    ],
    "name": "University of Medicine and Pharmacy of Targu Mures"
  },
  {
    "alpha_two_code": "RO",
    "state-province": null,
    "country": "Romania",
    "domains": [
      "umft.ro"
    ],
    "web_pages": [
      "http://www.umft.ro/"
    ],
    "name": "University of Medicine and Pharmacy of Timisoara"
  },
  {
    "alpha_two_code": "RO",
    "state-province": null,
    "country": "Romania",
    "domains": [
      "unarte.ro"
    ],
    "web_pages": [
      "http://www.unarte.ro/"
    ],
    "name": "National University of Arts"
  },
  {
    "alpha_two_code": "RO",
    "state-province": null,
    "country": "Romania",
    "domains": [
      "unatc.ro"
    ],
    "web_pages": [
      "http://www.unatc.ro/"
    ],
    "name": "National University of Theater and Film Arts"
  },
  {
    "alpha_two_code": "RO",
    "state-province": null,
    "country": "Romania",
    "domains": [
      "unibuc.ro"
    ],
    "web_pages": [
      "http://www.unibuc.ro/"
    ],
    "name": "University of Bucharest"
  },
  {
    "alpha_two_code": "RO",
    "state-province": null,
    "country": "Romania",
    "domains": [
      "unitbv.ro"
    ],
    "web_pages": [
      "http://www.unitbv.ro/"
    ],
    "name": "University \"Transilvany\" of Brasov"
  },
  {
    "alpha_two_code": "RO",
    "state-province": null,
    "country": "Romania",
    "domains": [
      "univagro-iasi.ro"
    ],
    "web_pages": [
      "http://www.univagro-iasi.ro/"
    ],
    "name": "University of Agriculture and Veterinary Medicine Iasi"
  },
  {
    "alpha_two_code": "RO",
    "state-province": null,
    "country": "Romania",
    "domains": [
      "univcb.ro"
    ],
    "web_pages": [
      "http://www.univcb.ro/"
    ],
    "name": "Constantin Brancoveanu University Pitesti"
  },
  {
    "alpha_two_code": "RO",
    "state-province": null,
    "country": "Romania",
    "domains": [
      "univermed-cdgm.ro"
    ],
    "web_pages": [
      "http://www.univermed-cdgm.ro/"
    ],
    "name": "University of Medicine and Pharmacy of Bucharest"
  },
  {
    "alpha_two_code": "RO",
    "state-province": null,
    "country": "Romania",
    "domains": [
      "universitateamaritima.ro"
    ],
    "web_pages": [
      "http://www.universitateamaritima.ro/"
    ],
    "name": "Maritime University Constanta"
  },
  {
    "alpha_two_code": "RO",
    "state-province": null,
    "country": "Romania",
    "domains": [
      "univ-ovidius.ro"
    ],
    "web_pages": [
      "http://www.univ-ovidius.ro/"
    ],
    "name": "University of Constanta"
  },
  {
    "alpha_two_code": "RO",
    "state-province": null,
    "country": "Romania",
    "domains": [
      "unmb.ro"
    ],
    "web_pages": [
      "http://www.unmb.ro/"
    ],
    "name": "National University of Music"
  },
  {
    "alpha_two_code": "RO",
    "state-province": null,
    "country": "Romania",
    "domains": [
      "uoradea.ro"
    ],
    "web_pages": [
      "http://www.uoradea.ro/"
    ],
    "name": "University of Oradea"
  },
  {
    "alpha_two_code": "RO",
    "state-province": null,
    "country": "Romania",
    "domains": [
      "upa.ro"
    ],
    "web_pages": [
      "http://www.upa.ro/"
    ],
    "name": "University \"Petre Andrei\" Iasi"
  },
  {
    "alpha_two_code": "RO",
    "state-province": null,
    "country": "Romania",
    "domains": [
      "upet.ro"
    ],
    "web_pages": [
      "http://www.upet.ro/"
    ],
    "name": "University of Petrosani"
  },
  {
    "alpha_two_code": "RO",
    "state-province": null,
    "country": "Romania",
    "domains": [
      "upg-ploiesti.ro"
    ],
    "web_pages": [
      "http://www.upg-ploiesti.ro/"
    ],
    "name": "University Oil- Gas Ploiesti"
  },
  {
    "alpha_two_code": "RO",
    "state-province": null,
    "country": "Romania",
    "domains": [
      "upit.ro"
    ],
    "web_pages": [
      "http://www.upit.ro/"
    ],
    "name": "University of Pitesti"
  },
  {
    "alpha_two_code": "RO",
    "state-province": null,
    "country": "Romania",
    "domains": [
      "upm.ro"
    ],
    "web_pages": [
      "http://www.upm.ro/"
    ],
    "name": "Petru Maior University of Targu Mures"
  },
  {
    "alpha_two_code": "RO",
    "state-province": null,
    "country": "Romania",
    "domains": [
      "usab.ro"
    ],
    "web_pages": [
      "http://www.usab.ro/"
    ],
    "name": "University of Agriculture and Veterinary Medicine Bucharest"
  },
  {
    "alpha_two_code": "RO",
    "state-province": null,
    "country": "Romania",
    "domains": [
      "usab-tm.ro"
    ],
    "web_pages": [
      "http://www.usab-tm.ro/"
    ],
    "name": "University of Agriculture and Veterinary Medicine Timisoara"
  },
  {
    "alpha_two_code": "RO",
    "state-province": null,
    "country": "Romania",
    "domains": [
      "usamvcluj.ro"
    ],
    "web_pages": [
      "http://www.usamvcluj.ro/"
    ],
    "name": "University of Agriculture and Veterinary Medicine Cluj-Napoca"
  },
  {
    "alpha_two_code": "RO",
    "state-province": null,
    "country": "Romania",
    "domains": [
      "usv.ro"
    ],
    "web_pages": [
      "http://www.usv.ro/"
    ],
    "name": "University of Suceava"
  },
  {
    "alpha_two_code": "RO",
    "state-province": null,
    "country": "Romania",
    "domains": [
      "utcb.ro"
    ],
    "web_pages": [
      "http://www.utcb.ro/"
    ],
    "name": "Technical University of Civil Engineering Bucharest"
  },
  {
    "alpha_two_code": "RO",
    "state-province": null,
    "country": "Romania",
    "domains": [
      "utcluj.ro"
    ],
    "web_pages": [
      "http://www.utcluj.ro/"
    ],
    "name": "Technical University of Cluj-Napoca"
  },
  {
    "alpha_two_code": "RO",
    "state-province": null,
    "country": "Romania",
    "domains": [
      "utgjiu.ro"
    ],
    "web_pages": [
      "http://www.utgjiu.ro/"
    ],
    "name": "University of Targu Jiu"
  },
  {
    "alpha_two_code": "RO",
    "state-province": null,
    "country": "Romania",
    "domains": [
      "utm.ro"
    ],
    "web_pages": [
      "http://www.utm.ro/"
    ],
    "name": "University \"Titu Maiorescu\""
  },
  {
    "alpha_two_code": "RO",
    "state-province": null,
    "country": "Romania",
    "domains": [
      "utt.ro"
    ],
    "web_pages": [
      "http://www.utt.ro/"
    ],
    "name": "Technical University of Timisoara"
  },
  {
    "alpha_two_code": "RO",
    "state-province": null,
    "country": "Romania",
    "domains": [
      "uvt.ro"
    ],
    "web_pages": [
      "http://www.uvt.ro/"
    ],
    "name": "West University of Timisoara"
  },
  {
    "alpha_two_code": "RO",
    "state-province": null,
    "country": "Romania",
    "domains": [
      "uvvg.ro"
    ],
    "web_pages": [
      "http://www.uvvg.ro/"
    ],
    "name": "Universitatea de Vest \"Vasile Goldiş\""
  },
  {
    "alpha_two_code": "RO",
    "state-province": null,
    "country": "Romania",
    "domains": [
      "valahia.ro"
    ],
    "web_pages": [
      "http://www.valahia.ro/"
    ],
    "name": "Valahia University of Targoviste"
  },
  {
    "alpha_two_code": "RO",
    "state-province": null,
    "country": "Romania",
    "domains": [
      "student.upt.ro",
      "upt.ro"
    ],
    "web_pages": [
      "https://upt.ro"
    ],
    "name": "Polytechnic University of Timisoara"
  }
]